qplanarity/__init__.py
qplanarity/linalg.py
qplanarity/main.py
qplanarity/qtutils.py
qplanarity-1.4.2.dist-info/LICENSE
qplanarity-1.4.2.dist-info/METADATA
qplanarity-1.4.2.dist-info/WHEEL
qplanarity-1.4.2.dist-info/entry_points.txt
qplanarity-1.4.2.dist-info/top_level.txt
qplanarity-1.4.2.dist-info/RECORD
