Metadata-Version: 2.1
Name: qplanarity
Version: 1.4.2
Summary: Puzzle game about untangling graphs
Home-page: https://gitlab.com/franksh/qplanarity
Author: Frank S. Hestvik
Author-email: tristesse@gmail.com
License: BSD3
Keywords: planarity,game,qt5,untangle,planar,graph,untangling
Platform: UNKNOWN
Classifier: Development Status :: 5 - Production/Stable
Classifier: License :: OSI Approved :: GNU General Public License v3 (GPLv3)
Classifier: Intended Audience :: End Users/Desktop
Classifier: Programming Language :: Python :: 3
Requires-Python: >=3.7
Requires-Dist: PyQt5
Requires-Dist: numpy
Requires-Dist: scipy
